spark_history_mcp/__init__.py
spark_history_mcp/api/__init__.py
spark_history_mcp/api/emr_persistent_ui_client.py
spark_history_mcp/api/spark_client.py
spark_history_mcp/api/spark_html_client.py
spark_history_mcp/config/__init__.py
spark_history_mcp/config/config.py
spark_history_mcp/core/__init__.py
spark_history_mcp/core/app.py
spark_history_mcp/core/main.py
spark_history_mcp/models/__init__.py
spark_history_mcp/models/mcp_types.py
spark_history_mcp/models/spark_types.py
spark_history_mcp/tools/__init__.py
spark_history_mcp/tools/tools.py
spark_history_mcp/utils/__init__.py
spark_history_mcp/utils/utils.py
mcp_apache_spark_history_server-0.1.4.dist-info/METADATA
mcp_apache_spark_history_server-0.1.4.dist-info/WHEEL
mcp_apache_spark_history_server-0.1.4.dist-info/entry_points.txt
mcp_apache_spark_history_server-0.1.4.dist-info/licenses/LICENSE
mcp_apache_spark_history_server-0.1.4.dist-info/RECORD
