Metadata-Version: 2.4
Name: mcp-apache-spark-history-server
Version: 0.1.4
Summary: Model Context Protocol (MCP) server for Apache Spark History Server with job comparison and analytics
Project-URL: Homepage, https://github.com/kubeflow/mcp-apache-spark-history-server
Project-URL: Repository, https://github.com/kubeflow/mcp-apache-spark-history-server
Project-URL: Issues, https://github.com/kubeflow/mcp-apache-spark-history-server/issues
Author-email: Manabu McCloskey <Manabu.McCloskey@gmail.com>, Vara Bonthu <vara.bonthu@gmail.com>
License: Apache-2.0
License-File: LICENSE
Keywords: analytics,history-server,mcp,model-context-protocol,performance,spark
Classifier: Development Status :: 3 - Alpha
Classifier: Intended Audience :: Developers
Classifier: License :: OSI Approved :: Apache Software License
Classifier: Programming Language :: Python :: 3.12
Classifier: Topic :: Scientific/Engineering :: Information Analysis
Classifier: Topic :: Software Development :: Libraries :: Python Modules
Classifier: Topic :: System :: Monitoring
Requires-Python: >=3.12
Requires-Dist: boto3~=1.34
Requires-Dist: mcp[cli]~=1.9
Requires-Dist: pydantic-settings>=2.9.1
Requires-Dist: pydantic~=2.4
Requires-Dist: pysocks>=1.7.1
Requires-Dist: pyyaml~=6.0
Requires-Dist: requests[socks]>=2.31.0
Requires-Dist: requests~=2.32.4
